forta_agent/__init__.py
forta_agent/alert.py
forta_agent/alert_event.py
forta_agent/alert_test.py
forta_agent/alerts_api.py
forta_agent/block.py
forta_agent/block_event.py
forta_agent/bloom_filter.py
forta_agent/bloom_filter_test.py
forta_agent/event_type.py
forta_agent/finding.py
forta_agent/jwt.py
forta_agent/jwt_test.py
forta_agent/label.py
forta_agent/labels_api.py
forta_agent/labels_api_test.py
forta_agent/network.py
forta_agent/receipt.py
forta_agent/trace.py
forta_agent/transaction.py
forta_agent/transaction_event.py
forta_agent/utils.py
forta_agent-0.1.27.dist-info/LICENSE
forta_agent-0.1.27.dist-info/METADATA
forta_agent-0.1.27.dist-info/WHEEL
forta_agent-0.1.27.dist-info/top_level.txt
forta_agent-0.1.27.dist-info/RECORD
