Metadata-Version: 2.1
Name: forta-agent
Version: 0.1.27
Summary: Forta Agent Python SDK
Home-page: https://forta.org/
Project-URL: Source, https://github.com/forta-network/forta-agent-sdk
Project-URL: Documentation, https://docs.forta.network/
Classifier: Programming Language :: Python :: 3
Classifier: License :: OSI Approved :: MIT License
Classifier: Operating System :: OS Independent
Requires-Python: >=3.6
License-File: LICENSE
Requires-Dist: jsonc-parser
Requires-Dist: web3 ==5.23.0
Requires-Dist: hexbytes
Requires-Dist: mmh3 ==3.0.0
